innerloop/__init__.py
innerloop/api.py
innerloop/call.py
innerloop/loop.py
innerloop/session.py
innerloop/structured.py
innerloop/truncate.py
innerloop/types.py
innerloop/extras/__init__.py
innerloop/extras/senpai/__init__.py
innerloop/extras/senpai/confidence.py
innerloop/extras/senpai/context_hash.py
innerloop/extras/senpai/events.py
innerloop/extras/senpai/kb_kit.py
innerloop/extras/senpai/kit.py
innerloop/extras/senpai/models.py
innerloop/extras/senpai/scripts.py
innerloop/extras/senpai/utils.py
innerloop/kits/__init__.py
innerloop/kits/base.py
innerloop/kits/safe_file.py
innerloop/kits/todo.py
innerloop/providers/__init__.py
innerloop/providers/anthropic.py
innerloop/providers/base.py
innerloop/providers/google.py
innerloop/providers/openai.py
innerloop/providers/routing.py
innerloop/providers/vertex.py
innerloop/schema/__init__.py
innerloop/schema/base.py
innerloop/schema/dict_backend.py
innerloop/schema/jsonschema_backend.py
innerloop/schema/msgspec_backend.py
innerloop/schema/null_backend.py
innerloop/schema/pydantic_backend.py
innerloop/schema/wrappers.py
innerloop/tooling/__init__.py
innerloop/tooling/base.py
innerloop/tooling/bash.py
innerloop/tooling/filesystem.py
innerloop/tooling/skill_tools.py
innerloop/tooling/skills.py
innerloop/tooling/web.py
innerloop-0.0.1.dev16.dist-info/METADATA
innerloop-0.0.1.dev16.dist-info/WHEEL
innerloop-0.0.1.dev16.dist-info/licenses/LICENSE
innerloop-0.0.1.dev16.dist-info/RECORD
