Metadata-Version: 2.4
Name: innerloop
Version: 0.0.1.dev16
Summary: LLM in a loop with tools, MCP, sessions, and structured outputs.
Project-URL: Homepage, https://github.com/botassembly/innerloop
Project-URL: Documentation, https://botassembly.org/innerloop
Project-URL: Repository, https://github.com/botassembly/innerloop
Project-URL: Issues, https://github.com/botassembly/innerloop/issues
Project-URL: Changelog, https://botassembly.org/innerloop/changelog/
Author-email: Ian Maurer <imaurer@gmail.com>
License-Expression: MIT
License-File: LICENSE
Keywords: agent,ai,anthropic,automation,claude,codex,devtool,gemini,llm,openai,sdk
Classifier: Development Status :: 3 - Alpha
Classifier: Intended Audience :: Developers
Classifier: License :: OSI Approved :: MIT License
Classifier: Operating System :: OS Independent
Classifier: Programming Language :: Python :: 3
Classifier: Programming Language :: Python :: 3.10
Classifier: Programming Language :: Python :: 3.11
Classifier: Programming Language :: Python :: 3.12
Classifier: Programming Language :: Python :: 3.13
Classifier: Programming Language :: Python :: 3.14
Classifier: Topic :: Scientific/Engineering :: Artificial Intelligence
Classifier: Topic :: Software Development :: Code Generators
Classifier: Topic :: Software Development :: Libraries :: Python Modules
Classifier: Typing :: Typed
Requires-Python: >=3.10
Requires-Dist: pydantic>=2.10.0
Requires-Dist: pyyaml>=6.0.0
Provides-Extra: all
Requires-Dist: anthropic>=0.40.0; extra == 'all'
Requires-Dist: beautifulsoup4>=4.12; extra == 'all'
Requires-Dist: google-generativeai>=0.8.0; extra == 'all'
Requires-Dist: httpx>=0.27.0; extra == 'all'
Requires-Dist: jsonschema>=4.20.0; extra == 'all'
Requires-Dist: msgspec>=0.19.0; extra == 'all'
Requires-Dist: openai>=1.50.0; extra == 'all'
Requires-Dist: trafilatura>=1.6; extra == 'all'
Requires-Dist: urllib3>=2.6.0; extra == 'all'
Provides-Extra: anthropic
Requires-Dist: anthropic>=0.40.0; extra == 'anthropic'
Provides-Extra: cloud
Requires-Dist: anthropic>=0.40.0; extra == 'cloud'
Requires-Dist: google-generativeai>=0.8.0; extra == 'cloud'
Requires-Dist: openai>=1.50.0; extra == 'cloud'
Provides-Extra: dev
Requires-Dist: anthropic>=0.40.0; extra == 'dev'
Requires-Dist: beautifulsoup4>=4.12; extra == 'dev'
Requires-Dist: google-generativeai>=0.8.0; extra == 'dev'
Requires-Dist: httpx>=0.27.0; extra == 'dev'
Requires-Dist: jsonschema>=4.20.0; extra == 'dev'
Requires-Dist: msgspec>=0.19.0; extra == 'dev'
Requires-Dist: mypy>=1.8.0; extra == 'dev'
Requires-Dist: openai>=1.50.0; extra == 'dev'
Requires-Dist: pytest-asyncio>=0.21.0; extra == 'dev'
Requires-Dist: pytest-cov>=4.1.0; extra == 'dev'
Requires-Dist: pytest-mock>=3.11.0; extra == 'dev'
Requires-Dist: pytest>=7.4.0; extra == 'dev'
Requires-Dist: python-dotenv>=1.0.0; extra == 'dev'
Requires-Dist: trafilatura>=1.6; extra == 'dev'
Requires-Dist: urllib3>=2.6.0; extra == 'dev'
Provides-Extra: google
Requires-Dist: google-generativeai>=0.8.0; extra == 'google'
Provides-Extra: jsonschema
Requires-Dist: jsonschema>=4.20.0; extra == 'jsonschema'
Provides-Extra: lmstudio
Requires-Dist: openai>=1.50.0; extra == 'lmstudio'
Provides-Extra: msgspec
Requires-Dist: msgspec>=0.19.0; extra == 'msgspec'
Provides-Extra: ollama
Requires-Dist: openai>=1.50.0; extra == 'ollama'
Provides-Extra: openai
Requires-Dist: openai>=1.50.0; extra == 'openai'
Provides-Extra: vertex
Requires-Dist: google-cloud-aiplatform>=1.38.0; extra == 'vertex'
Provides-Extra: web
Requires-Dist: beautifulsoup4>=4.12; extra == 'web'
Requires-Dist: httpx>=0.27.0; extra == 'web'
Requires-Dist: trafilatura>=1.6; extra == 'web'
Requires-Dist: urllib3>=2.6.0; extra == 'web'
